watchdog_gevent/__init__.py
watchdog_gevent/observers.py
watchdog_gevent-0.2.1.dist-info/LICENSE
watchdog_gevent-0.2.1.dist-info/METADATA
watchdog_gevent-0.2.1.dist-info/WHEEL
watchdog_gevent-0.2.1.dist-info/top_level.txt
watchdog_gevent-0.2.1.dist-info/RECORD
